threaded_fetcher/__init__.py
threaded_fetcher/__version__.py
threaded_fetcher/cli.py
threaded_fetcher/fetcher.py
threaded_fetcher/utils.py
threaded_fetcher-0.2.1.dist-info/licenses/LICENSE
threaded_fetcher-0.2.1.dist-info/METADATA
threaded_fetcher-0.2.1.dist-info/WHEEL
threaded_fetcher-0.2.1.dist-info/entry_points.txt
threaded_fetcher-0.2.1.dist-info/top_level.txt
threaded_fetcher-0.2.1.dist-info/RECORD
