Metadata-Version: 2.4
Name: threaded-fetcher
Version: 0.2.1
Summary: Concurrent threaded URL fetcher for data engineering workflows
Author-email: "S.Sanjay" <sanjays13022003@gmail.com>
License: MIT
Keywords: threading,fetch,http,scrape,data-engineering,cli
Classifier: Programming Language :: Python :: 3
Classifier: License :: OSI Approved :: MIT License
Classifier: Operating System :: OS Independent
Requires-Python: >=3.8
License-File: LICENSE
Requires-Dist: requests>=2.28
Requires-Dist: pandas>=2.0
Requires-Dist: colorama>=0.4
Requires-Dist: openpyxl>=3.0
Requires-Dist: pyarrow>=8.0
Dynamic: license-file
